rtfparse/__about__.py
rtfparse/__init__.py
rtfparse/cli.py
rtfparse/entities.py
rtfparse/enums.py
rtfparse/logging_conf.py
rtfparse/minimal.py
rtfparse/parser.py
rtfparse/re_patterns.py
rtfparse/utils.py
rtfparse/renderers/__init__.py
rtfparse/renderers/html_decapsulator.py
rtfparse-0.9.5.dist-info/METADATA
rtfparse-0.9.5.dist-info/WHEEL
rtfparse-0.9.5.dist-info/entry_points.txt
rtfparse-0.9.5.dist-info/licenses/LICENSE
rtfparse-0.9.5.dist-info/RECORD
