Metadata-Version: 2.4
Name: rtfparse
Version: 0.9.5
Summary: Tool to parse Microsoft Rich Text Format (RTF)
Project-URL: Documentation, https://github.com/fleetingbytes/rtfparse#readme
Project-URL: Issues, https://github.com/fleetingbytes/rtfparse/issues
Project-URL: Source, https://github.com/fleetingbytes/rtfparse
Author-email: Sven Siegmund <sven.siegmund@iav.de>
License-Expression: MIT
License-File: LICENSE
Keywords: parse,rtf
Classifier: Development Status :: 5 - Production/Stable
Classifier: Environment :: Console
Classifier: Intended Audience :: Developers
Classifier: Natural Language :: English
Classifier: Operating System :: MacOS :: MacOS X
Classifier: Operating System :: Microsoft :: Windows
Classifier: Operating System :: OS Independent
Classifier: Operating System :: POSIX :: Linux
Classifier: Programming Language :: Python :: 3.10
Classifier: Programming Language :: Python :: 3.11
Classifier: Topic :: Software Development :: Testing
Classifier: Topic :: Utilities
Requires-Python: >=3.10
Requires-Dist: argcomplete
Requires-Dist: compressed-rtf
Requires-Dist: extract-msg
Requires-Dist: provide-dir
